[
  {
    "type": "text",
    "validation_regex": "",
    "label": "collection ID",
    "name": "collection_id"
  },
  {
    "children": [
      {
        "allow_new_line": false,
        "display_width": null,
        "label": "ProductId",
        "locked": false,
        "name": "productid",
        "placeholder": "Product Id",
        "required": false,
        "show_emoji_picker": false,
        "type": "text",
        "validation_regex": ""
      },
      {
        "type": "group",
        "label": "Value added services",
        "children": [
          {
            "type": "text",

            "validation_regex": "",
            "label": "Value added services text",
            "name": "value_added_services_text"
          },
          {
            "type": "text",
            "validation_regex": "",
            "label": "Value added services tooltip text",
            "name": "value_added_services_tooltip_text"
          },
          {
            "type": "image",
            "default": {
              "size_type": "auto",
              "src": "",
              "alt": null,
              "loading": "lazy"
            },
            "resizable": true,
            "responsive": true,
            "show_loading": false,
            "label": "Value added services tooltip image",
            "name": "value_added_services_tooltip_image"
          }
        ],
        "name": "value_added_services",
        "default": {
          "value_added_services_tooltip_image": {
            "size_type": "auto",
            "src": "",
            "alt": null,
            "loading": "lazy"
          }
        },
        "occurrence": {}
      },
      {
        "type": "group",
        "label": "Secifications",
        "children": [
          {
            "type": "text",

            "validation_regex": "",
            "label": "Secifications  Text",
            "name": "secifications_text"
          },
          {
            "type": "image",
            "default": {
              "size_type": "auto",
              "src": "",
              "alt": null,
              "loading": "lazy"
            },
            "resizable": true,
            "responsive": true,
            "show_loading": false,
            "label": "Secification image",
            "name": "secification_image"
          }
        ],
        "name": "secifications",
        "default": {
          "secification_image": {
            "size_type": "auto",
            "src": "",
            "alt": null,
            "loading": "lazy"
          }
        },
        "occurrence": {}
      },
      {
        "default": {
          "size_type": "auto",
          "src": "",
          "alt": null,
          "loading": "lazy"
        },
        "display_width": null,
        "label": "Accepted Payments icons",
        "locked": false,
        "name": "accepted_payments",
        "required": false,
        "resizable": true,
        "responsive": true,
        "show_loading": false,
        "type": "image",
        "occurrence": {}
      },
      {
        "allow_new_line": false,
        "display_width": null,
        "label": "Accepted Payments Heading",
        "locked": false,
        "name": "accepted_payments_heading",
        "placeholder": "",
        "required": false,
        "show_emoji_picker": false,
        "type": "text",
        "validation_regex": ""
      },

      {
        "allow_new_line": false,
        "default": "product description",
        "display_width": null,
        "label": "Product Description",
        "locked": false,
        "name": "heading",
        "required": false,
        "show_emoji_picker": true,
        "type": "text",
        "validation_regex": ""
      }
    ],
    "default": {
      "product_image": {
        "size_type": "auto",
        "src": "",
        "alt": null,
        "loading": "lazy"
      },
      "heading": "hello world"
    },
    "display_width": null,
    "expanded": false,
    "label": "Product Item",
    "locked": false,
    "name": "product_item",
    "occurrence": {},
    "required": false,
    "tab": "CONTENT",
    "type": "group"
  }
]
